{
  "id": "faq",
  "title": "частые вопросы",
  "list": [
    {
      "name": "Работаете ли вы с электронным документооборотом?",
      "text": "Да, работаем. Используем СБИС."
    },
    {
      "name": "Откуда вы можете забрать товар?",
      "text": "Мы можем забрать ваш товар из любой точки Москвы. Например, ТК «Южные Ворота», ТЯК «Москва», ТК «Садовод»."
    },
    {
      "name": "Как вы упаковываете товары?",
      "text": "Товары упакуем по правилам маркетплейса в вашу или нашу упаковку."
    },
    {
      "name": "С какими маркетплейсами вы работаете?",
      "text": "Мы работаем с Wildberries, Яндекс.Маркет, Ozon, СберМаркет."
    },
    {
      "name": "Когда происходит оплата?",
      "text": "В день отгрузки вашего товара на маркетплейс."
    },
    {
      "name": "Можете ли вы срочно отгрузить и упаковать товар?",
      "text": "Да. <br> Можем отгрузить и упаковать день в день!"
    },
    {
      "name": "Я хочу заказать небольшую партию товара из Китая. Это возможно?",
      "text": "Да! Главное, чтобы вес товара превышал 7 кг. Ограничений по стоимости нет."
    },
    {
      "name": "Сколько времени занимает весь процесс от подбора товара на торговых площадках Китая до доставки на склад в Москве?",
      "text": "Обычно 2-3 недели."
    },
    {
      "name": "Предоставляете ли вы скидки и кому?",
      "text": "<ul><li>мы предлагаем особые выгодные условия на&nbsp;самый первый заказ</li><li>у нас действуют постоянные акции</li><li>мы делаем скидки при большом объеме заказа</li></ul>"
    }
  ]
}
